monitorpeek/__init__.py
monitorpeek/final_icon.ico
monitorpeek/main.py
monitorpeek-2.1.5.dist-info/METADATA
monitorpeek-2.1.5.dist-info/WHEEL
monitorpeek-2.1.5.dist-info/entry_points.txt
monitorpeek-2.1.5.dist-info/top_level.txt
monitorpeek-2.1.5.dist-info/RECORD
