Metadata-Version: 2.1
Name: monitorpeek
Version: 2.1.5
Summary: A real-time secondary monitor preview tool with cursor tracking
Home-page: https://github.com/zorat111/MonitorPeek
Author: John
Author-email: zorat@abv.bg
License: UNKNOWN
Platform: UNKNOWN
Classifier: Programming Language :: Python :: 3
Classifier: License :: OSI Approved :: MIT License
Classifier: Operating System :: Microsoft :: Windows
Classifier: Environment :: Win32 (MS Windows)
Classifier: Topic :: Utilities
Requires-Python: >=3.8
Requires-Dist: PyQt6>=6.4.0
Requires-Dist: opencv-python>=4.7.0
Requires-Dist: numpy>=1.24.0
Requires-Dist: mss>=9.0.1
Requires-Dist: pywin32>=305
